<DOMSymbolItem xmlns:xsi="http://www.w3.org/2001/XMLSchema-instance" xmlns="http://ns.adobe.com/xfl/2008/" name="panels/tabs/GlossaryTabLabel" itemID="5140ddfd-0000089f" symbolType="button" lastModified="1385062261" lastUniqueIdentifier="2">
  <timeline>
    <DOMTimeline name="GlossaryTabLabel">
      <layers>
        <DOMLayer name="Label" color="#9933CC" locked="true" current="true" isSelected="true" autoNamed="false">
          <frames>
            <DOMFrame index="0" duration="4" keyMode="9728">
              <elements>
                <DOMDynamicText name="label" selected="true" width="78" height="15.05" isSelectable="false">
                  <matrix>
                    <Matrix tx="2" ty="7.4"/>
                  </matrix>
                  <textRuns>
                    <DOMTextRun>
                      <characters>Glossary</characters>
                      <textAttrs>
                        <DOMTextAttrs alignment="center" aliasText="false" size="13" bitmapSize="260" face="Articulate Bold*"/>
                      </textAttrs>
                    </DOMTextRun>
                  </textRuns>
                </DOMDynamicText>
              </elements>
            </DOMFrame>
          </frames>
        </DOMLayer>
        <DOMLayer name="Background" color="#4FFF4F" locked="true" autoNamed="false">
          <frames>
            <DOMFrame index="0" duration="3" keyMode="9728">
              <elements/>
            </DOMFrame>
            <DOMFrame index="3" keyMode="9728">
              <elements>
                <DOMSymbolInstance libraryItemName="panels/tabs/Tab" centerPoint3DX="41" centerPoint3DY="15">
                  <matrix>
                    <Matrix a="1.1156005859375"/>
                  </matrix>
                  <transformationPoint>
                    <Point x="36.75" y="15"/>
                  </transformationPoint>
                </DOMSymbolInstance>
              </elements>
            </DOMFrame>
          </frames>
        </DOMLayer>
      </layers>
    </DOMTimeline>
  </timeline>
</DOMSymbolItem>